Lab5/demuxDF.v
//dataflow demux code

module demuxDF(
    input wire in,
    input wire [2:0] sel,
    output wire [7:0] out
);

    assign out[0] = (sel[2] == 0 && sel[1] == 0 && sel[0] == 0) ? in : 1'b0;
    assign out[1] = (sel[2] == 0 && sel[1] == 0 && sel[0] == 1) ? in : 1'b0;
    assign out[2] = (sel[2] == 0 && sel[1] == 1 && sel[0] == 0) ? in : 1'b0;
    assign out[3] = (sel[2] == 0 && sel[1] == 1 && sel[0] == 1) ? in : 1'b0;
    assign out[4] = (sel[2] == 1 && sel[1] == 0 && sel[0] == 0) ? in : 1'b0;
    assign out[5] = (sel[2] == 1 && sel[1] == 0 && sel[0] == 1) ? in : 1'b0;
    assign out[6] = (sel[2] == 1 && sel[1] == 1 && sel[0] == 0) ? in : 1'b0;
    assign out[7] = (sel[2] == 1 && sel[1] == 1 && sel[0] == 1) ? in : 1'b0;

endmodule


module tb_demuxDF;

    reg IN;
    reg [2:0] SEL;
    wire [7:0] OUT;

    demuxDF uut (.in(IN), .sel(SEL), .out(OUT));

    initial begin

        //gtk wave
        $dumpfile("demuxGL.vcd");
        $dumpvars(0, tb_demuxDF);

        IN = 1'b1;
        
        $display("Input is : %b", IN);

        $display("Selector | OUT");

        SEL = 3'b000; #1 $display("   %b   | %b", SEL, OUT);
        SEL = 3'b001; #1 $display("   %b   | %b", SEL, OUT);
        SEL = 3'b010; #1 $display("   %b   | %b", SEL, OUT);
        SEL = 3'b011; #1 $display("   %b   | %b", SEL, OUT);
        SEL = 3'b100; #1 $display("   %b   | %b", SEL, OUT);
        SEL = 3'b101; #1 $display("   %b   | %b", SEL, OUT);
        SEL = 3'b110; #1 $display("   %b   | %b", SEL, OUT);
        SEL = 3'b111; #1 $display("   %b   | %b", SEL, OUT);
        
        $finish;
    end

endmodule

Lab5/demuxGL.vcd
$date
	Mon Sep 22 10:40:12 2025
$end
$version
	Icarus Verilog
$end
$timescale
	1s
$end
$scope module tb_demuxDF $end
$var wire 8 ! OUT [7:0] $end
$var reg 1 " IN $end
$var reg 3 # SEL [2:0] $end
$scope module uut $end
$var wire 1 " in $end
$var wire 3 $ sel [2:0] $end
$var wire 8 % out [7:0] $end
$upscope $end
$upscope $end
$enddefinitions $end
$comment Show the parameter values. $end
$dumpall
$end
#0
$dumpvars
b1 %
b0 $
b0 #
1"
b1 !
$end
#1
b10 !
b10 %
b1 #
b1 $
#2
b100 !
b100 %
b10 #
b10 $
#3
b1000 !
b1000 %
b11 #
b11 $
#4
b10000 !
b10000 %
b100 #
b100 $
#5
b100000 !
b100000 %
b101 #
b101 $
#6
b1000000 !
b1000000 %
b110 #
b110 $
#7
b10000000 !
b10000000 %
b111 #
b111 $
